{
  "gangsta": {
    "total": 1,
    "forms": {
      "gangsta": 1
    }
  },
  "exodus": {
    "total": 1,
    "forms": {
      "exodus": 1
    }
  },
  "cameraman": {
    "total": 1,
    "forms": {
      "cameraman": 1
    }
  },
  "terrorise": {
    "total": 1,
    "forms": {
      "terrorised": 1
    }
  },
  "wrongdoing": {
    "total": 1,
    "forms": {
      "wrongdoings": 1
    }
  },
  "ferociously": {
    "total": 1,
    "forms": {
      "ferociously": 1
    }
  },
  "easter": {
    "total": 1,
    "forms": {
      "easter": 1
    }
  },
  "greatly": {
    "total": 1,
    "forms": {
      "greatly": 1
    }
  },
  "norbert": {
    "total": 1,
    "forms": {
      "norbert": 1
    }
  },
  "banono": {
    "total": 1,
    "forms": {
      "banono": 1
    }
  },
  "emergence": {
    "total": 1,
    "forms": {
      "emergence": 1
    }
  },
  "boukere": {
    "total": 1,
    "forms": {
      "boukere": 1
    }
  },
  "raa": {
    "total": 1,
    "forms": {
      "raa": 1
    }
  },
  "kaba": {
    "total": 1,
    "forms": {
      "kaba": 1
    }
  },
  "ank": {
    "total": 1,
    "forms": {
      "ank": 1
    }
  },
  "tuba": {
    "total": 1,
    "forms": {
      "tuba": 1
    }
  },
  "tendency": {
    "total": 1,
    "forms": {
      "tendency": 1
    }
  },
  "ratch": {
    "total": 1,
    "forms": {
      "ratch": 1
    }
  },
  "ooturi": {
    "total": 1,
    "forms": {
      "ooturi": 1
    }
  },
  "aled": {
    "total": 1,
    "forms": {
      "aled": 1
    }
  },
  "parental": {
    "total": 1,
    "forms": {
      "parental": 1
    }
  },
  "malakika": {
    "total": 1,
    "forms": {
      "malakika": 1
    }
  },
  "malaki": {
    "total": 1,
    "forms": {
      "malaki": 1
    }
  },
  "aimless": {
    "total": 1,
    "forms": {
      "aimless": 1
    }
  },
  "batica": {
    "total": 1,
    "forms": {
      "batica": 1
    }
  },
  "tota": {
    "total": 1,
    "forms": {
      "tota": 1
    }
  },
  "feally": {
    "total": 1,
    "forms": {
      "feally": 1
    }
  },
  "malap": {
    "total": 1,
    "forms": {
      "malap": 1
    }
  },
  "macolo": {
    "total": 1,
    "forms": {
      "macolo": 1
    }
  },
  "freind": {
    "total": 1,
    "forms": {
      "freind": 1
    }
  },
  "oc": {
    "total": 1,
    "forms": {
      "oc": 1
    }
  },
  "italis": {
    "total": 1,
    "forms": {
      "italis": 1
    }
  },
  "tolatino": {
    "total": 1,
    "forms": {
      "tolatino": 1
    }
  },
  "tizza": {
    "total": 1,
    "forms": {
      "tizza": 1
    }
  },
  "delacta": {
    "total": 1,
    "forms": {
      "delacta": 1
    }
  },
  "coalva": {
    "total": 1,
    "forms": {
      "coalva": 1
    }
  },
  "mopa": {
    "total": 1,
    "forms": {
      "mopa": 1
    }
  },
  "bogger": {
    "total": 1,
    "forms": {
      "bogger's": 1
    },
    "expansions": {
      "bogger's": "bogger's (possessive)"
    }
  },
  "quita": {
    "total": 1,
    "forms": {
      "quita": 1
    }
  },
  "comy": {
    "total": 1,
    "forms": {
      "comy": 1
    }
  },
  "yoke": {
    "total": 1,
    "forms": {
      "yoking": 1
    }
  },
  "porn": {
    "total": 1,
    "forms": {
      "porn": 1
    }
  },
  "macalino": {
    "total": 1,
    "forms": {
      "macalino": 1
    }
  },
  "statch": {
    "total": 1,
    "forms": {
      "statch": 1
    }
  },
  "fuka": {
    "total": 1,
    "forms": {
      "fuka": 1
    }
  },
  "jony": {
    "total": 1,
    "forms": {
      "jony": 1
    }
  },
  "etoile": {
    "total": 1,
    "forms": {
      "etoile": 1
    }
  },
  "ruze": {
    "total": 1,
    "forms": {
      "ruze": 1
    }
  },
  "naki": {
    "total": 1,
    "forms": {
      "naki's": 1
    },
    "expansions": {
      "naki's": "naki's (possessive)"
    }
  },
  "chipolata": {
    "total": 1,
    "forms": {
      "chipolata": 1
    }
  },
  "chipo": {
    "total": 1,
    "forms": {
      "chipo": 1
    }
  },
  "takalido": {
    "total": 1,
    "forms": {
      "takalido": 1
    }
  },
  "cashmi": {
    "total": 1,
    "forms": {
      "cashmi": 1
    }
  },
  "libido": {
    "total": 1,
    "forms": {
      "libido": 1
    }
  },
  "turtleneck": {
    "total": 1,
    "forms": {
      "turtleneck": 1
    }
  },
  "miniskirt": {
    "total": 1,
    "forms": {
      "miniskirts": 1
    }
  },
  "va": {
    "total": 1,
    "forms": {
      "va": 1
    }
  },
  "yva": {
    "total": 1,
    "forms": {
      "yva": 1
    }
  },
  "lak": {
    "total": 1,
    "forms": {
      "lak": 1
    }
  },
  "pawani": {
    "total": 1,
    "forms": {
      "pawani": 1
    }
  },
  "tul": {
    "total": 1,
    "forms": {
      "tul": 1
    }
  },
  "macumba": {
    "total": 1,
    "forms": {
      "macumba": 1
    }
  },
  "paso": {
    "total": 1,
    "forms": {
      "paso": 1
    }
  },
  "clota": {
    "total": 1,
    "forms": {
      "clota": 1
    }
  },
  "cavadi": {
    "total": 1,
    "forms": {
      "cavadi": 1
    }
  },
  "oskova": {
    "total": 1,
    "forms": {
      "oskova": 1
    }
  },
  "emalako": {
    "total": 1,
    "forms": {
      "emalako": 1
    }
  },
  "melatoni": {
    "total": 1,
    "forms": {
      "melatoni": 1
    }
  },
  "topinanbol": {
    "total": 1,
    "forms": {
      "topinanbol": 1
    }
  },
  "polecopa": {
    "total": 1,
    "forms": {
      "polecopa": 1
    }
  },
  "potin": {
    "total": 1,
    "forms": {
      "potin": 1
    }
  },
  "tropa": {
    "total": 1,
    "forms": {
      "tropa": 1
    }
  },
  "calmos": {
    "total": 1,
    "forms": {
      "calmos": 1
    }
  },
  "mova": {
    "total": 1,
    "forms": {
      "mova": 1
    }
  },
  "finte": {
    "total": 1,
    "forms": {
      "finte": 1
    }
  },
  "underworld": {
    "total": 1,
    "forms": {
      "underworld": 1
    }
  },
  "cavatika": {
    "total": 1,
    "forms": {
      "cavatika": 1
    }
  },
  "pulino": {
    "total": 1,
    "forms": {
      "pulino": 1
    }
  },
  "callo": {
    "total": 1,
    "forms": {
      "callo": 1
    }
  },
  "olatino": {
    "total": 1,
    "forms": {
      "olatino": 1
    }
  },
  "lakapa": {
    "total": 1,
    "forms": {
      "lakapa": 1
    }
  },
  "makalouf": {
    "total": 1,
    "forms": {
      "makalouf": 1
    }
  },
  "palayo": {
    "total": 1,
    "forms": {
      "palayo": 1
    }
  },
  "bisetto": {
    "total": 1,
    "forms": {
      "bisetto": 1
    }
  },
  "kasos": {
    "total": 1,
    "forms": {
      "kasos": 1
    }
  },
  "potakino": {
    "total": 1,
    "forms": {
      "potakino": 1
    }
  },
  "sugarplum": {
    "total": 1,
    "forms": {
      "sugarplum": 1
    }
  },
  "topalino": {
    "total": 1,
    "forms": {
      "topalino": 1
    }
  },
  "arrabiata": {
    "total": 1,
    "forms": {
      "arrabiata": 1
    }
  },
  "lito": {
    "total": 1,
    "forms": {
      "lito": 1
    }
  },
  "toooo": {
    "total": 1,
    "forms": {
      "toooo": 1
    }
  },
  "vichyay": {
    "total": 1,
    "forms": {
      "vichyay": 1
    }
  },
  "vano": {
    "total": 1,
    "forms": {
      "vano": 1
    }
  },
  "chyay": {
    "total": 1,
    "forms": {
      "chyay": 1
    }
  },
  "ikatrouv": {
    "total": 1,
    "forms": {
      "ikatrouv": 1
    }
  },
  "pasc": {
    "total": 1,
    "forms": {
      "pasc": 1
    }
  },
  "dumo": {
    "total": 1,
    "forms": {
      "dumo": 1
    }
  },
  "eli": {
    "total": 1,
    "forms": {
      "eli": 1
    }
  },
  "pigtail": {
    "total": 1,
    "forms": {
      "pigtails": 1
    }
  },
  "popapeil": {
    "total": 1,
    "forms": {
      "popapeil": 1
    }
  }
}