{
  "ukkepuk": {
    "total": 1,
    "forms": {
      "ukkepuk": 1
    }
  },
  "dojo": {
    "total": 1,
    "forms": {
      "dojo": 1
    }
  },
  "handheld": {
    "total": 1,
    "forms": {
      "handheld": 1
    }
  },
  "dua": {
    "total": 1,
    "forms": {
      "dua": 1
    }
  },
  "lipa": {
    "total": 1,
    "forms": {
      "lipa": 1
    }
  },
  "puste": {
    "total": 1,
    "forms": {
      "puste": 1
    }
  },
  "oeh": {
    "total": 1,
    "forms": {
      "oeh": 1
    }
  },
  "pfjoew": {
    "total": 1,
    "forms": {
      "pfjoew": 1
    }
  },
  "hoi": {
    "total": 1,
    "forms": {
      "hoi": 1
    }
  },
  "avid": {
    "total": 1,
    "forms": {
      "avid": 1
    }
  },
  "decisive": {
    "total": 1,
    "forms": {
      "decisive": 1
    }
  },
  "unleaded": {
    "total": 1,
    "forms": {
      "unleaded": 1
    }
  },
  "pricey": {
    "total": 1,
    "forms": {
      "pricey": 1
    }
  },
  "unreadable": {
    "total": 1,
    "forms": {
      "unreadable": 1
    }
  },
  "liter": {
    "total": 1,
    "forms": {
      "liters": 1
    }
  },
  "lekker": {
    "total": 1,
    "forms": {
      "lekker": 1
    }
  },
  "puh": {
    "total": 1,
    "forms": {
      "puh": 1
    }
  },
  "granola": {
    "total": 1,
    "forms": {
      "granola": 1
    }
  },
  "muesli": {
    "total": 1,
    "forms": {
      "muesli": 1
    }
  },
  "podcast": {
    "total": 1,
    "forms": {
      "podcast": 1
    }
  },
  "hairdresser": {
    "total": 1,
    "forms": {
      "hairdresser": 1
    }
  },
  "bove": {
    "total": 1,
    "forms": {
      "bove": 1
    }
  },
  "smartass": {
    "total": 1,
    "forms": {
      "smartass": 1
    }
  },
  "villainess": {
    "total": 1,
    "forms": {
      "villainess": 1
    }
  },
  "expertly": {
    "total": 1,
    "forms": {
      "expertly": 1
    }
  },
  "blackmail": {
    "total": 1,
    "forms": {
      "blackmail": 1
    }
  },
  "suppository": {
    "total": 1,
    "forms": {
      "suppository": 1
    }
  },
  "colada": {
    "total": 1,
    "forms": {
      "colada": 1
    }
  },
  "bellos": {
    "total": 1,
    "forms": {
      "bellos": 1
    }
  },
  "cafe": {
    "total": 1,
    "forms": {
      "cafe": 1
    }
  },
  "pfiew": {
    "total": 1,
    "forms": {
      "pfiew": 1
    }
  },
  "destructo": {
    "total": 1,
    "forms": {
      "destructo": 1
    }
  },
  "driller": {
    "total": 1,
    "forms": {
      "driller": 1
    }
  },
  "tiramisu": {
    "total": 1,
    "forms": {
      "tiramisu": 1
    }
  },
  "downy": {
    "total": 1,
    "forms": {
      "downy": 1
    }
  },
  "cunninghammetjes": {
    "total": 1,
    "forms": {
      "cunninghammetjes": 1
    }
  },
  "ehm": {
    "total": 1,
    "forms": {
      "ehm": 1
    }
  },
  "favo": {
    "total": 1,
    "forms": {
      "favo": 1
    }
  },
  "brussels": {
    "total": 1,
    "forms": {
      "brussels": 1
    }
  },
  "oahu": {
    "total": 1,
    "forms": {
      "oahu": 1
    }
  },
  "yeehaa": {
    "total": 1,
    "forms": {
      "yeehaa": 1
    }
  },
  "yiehaa": {
    "total": 1,
    "forms": {
      "yiehaa": 1
    }
  },
  "iew": {
    "total": 1,
    "forms": {
      "iew": 1
    }
  },
  "antipasti": {
    "total": 1,
    "forms": {
      "antipasti": 1
    }
  },
  "coaster": {
    "total": 1,
    "forms": {
      "coaster": 1
    }
  },
  "commode": {
    "total": 1,
    "forms": {
      "commode": 1
    }
  },
  "giza": {
    "total": 1,
    "forms": {
      "giza": 1
    }
  },
  "inflatable": {
    "total": 1,
    "forms": {
      "inflatable": 1
    }
  },
  "throo": {
    "total": 1,
    "forms": {
      "throo": 1
    }
  },
  "eiffel": {
    "total": 1,
    "forms": {
      "eiffel": 1
    }
  },
  "chillax": {
    "total": 1,
    "forms": {
      "chillax": 1
    }
  },
  "choco": {
    "total": 1,
    "forms": {
      "choco": 1
    }
  },
  "neil": {
    "total": 1,
    "forms": {
      "neil": 1
    }
  },
  "nasa": {
    "total": 1,
    "forms": {
      "nasa": 1
    }
  },
  "mathematical": {
    "total": 1,
    "forms": {
      "mathematical": 1
    }
  },
  "audacity": {
    "total": 1,
    "forms": {
      "audacity": 1
    }
  },
  "claustrophobic": {
    "total": 1,
    "forms": {
      "claustrophobic": 1
    }
  },
  "background": {
    "total": 1,
    "forms": {
      "background": 1
    }
  },
  "knighthood": {
    "total": 1,
    "forms": {
      "knighthood": 1
    }
  },
  "dealio": {
    "total": 1,
    "forms": {
      "dealio": 1
    }
  },
  "cheeto": {
    "total": 1,
    "forms": {
      "cheeto": 1
    }
  },
  "nonstick": {
    "total": 1,
    "forms": {
      "nonstick": 1
    }
  },
  "mouthwash": {
    "total": 1,
    "forms": {
      "mouthwash": 1
    }
  },
  "yello": {
    "total": 1,
    "forms": {
      "yello": 1
    }
  },
  "scarily": {
    "total": 1,
    "forms": {
      "scarily": 1
    }
  },
  "excerpt": {
    "total": 1,
    "forms": {
      "excerpt": 1
    }
  },
  "tude": {
    "total": 1,
    "forms": {
      "tude": 1
    }
  },
  "toffee": {
    "total": 1,
    "forms": {
      "toffee": 1
    }
  },
  "tote": {
    "total": 1,
    "forms": {
      "totes": 1
    }
  },
  "caramel": {
    "total": 1,
    "forms": {
      "caramel": 1
    }
  },
  "clumpies": {
    "total": 1,
    "forms": {
      "clumpies": 1
    }
  },
  "funnest": {
    "total": 1,
    "forms": {
      "funnest": 1
    }
  },
  "frowny": {
    "total": 1,
    "forms": {
      "frowny": 1
    }
  },
  "optimum": {
    "total": 1,
    "forms": {
      "optimum": 1
    }
  },
  "bathtub": {
    "total": 1,
    "forms": {
      "bathtub": 1
    }
  },
  "literature": {
    "total": 1,
    "forms": {
      "literature": 1
    }
  },
  "reply": {
    "total": 1,
    "forms": {
      "replied": 1
    }
  },
  "sarcastically": {
    "total": 1,
    "forms": {
      "sarcastically": 1
    }
  },
  "maliciously": {
    "total": 1,
    "forms": {
      "maliciously": 1
    }
  },
  "gallant": {
    "total": 1,
    "forms": {
      "gallant": 1
    }
  },
  "jills": {
    "total": 1,
    "forms": {
      "jills": 1
    }
  },
  "bogus": {
    "total": 1,
    "forms": {
      "bogus": 1
    }
  },
  "fuji": {
    "total": 1,
    "forms": {
      "fuji": 1
    }
  },
  "arctic": {
    "total": 1,
    "forms": {
      "arctic": 1
    }
  },
  "transmutation": {
    "total": 1,
    "forms": {
      "transmutation": 1
    }
  },
  "chem": {
    "total": 1,
    "forms": {
      "chem": 1
    }
  },
  "tasing": {
    "total": 1,
    "forms": {
      "tasing": 1
    }
  },
  "sheepsbutt": {
    "total": 1,
    "forms": {
      "sheepsbutt": 1
    }
  },
  "gruties": {
    "total": 1,
    "forms": {
      "gruties": 1
    }
  },
  "donnie": {
    "total": 1,
    "forms": {
      "donnie": 1
    }
  },
  "gollum": {
    "total": 1,
    "forms": {
      "gollum": 1
    }
  },
  "jujitsu": {
    "total": 1,
    "forms": {
      "jujitsu": 1
    }
  },
  "krav": {
    "total": 1,
    "forms": {
      "krav": 1
    }
  },
  "maga": {
    "total": 1,
    "forms": {
      "maga": 1
    }
  },
  "aztec": {
    "total": 1,
    "forms": {
      "aztec": 1
    }
  },
  "warfare": {
    "total": 1,
    "forms": {
      "warfare": 1
    }
  },
  "krumping": {
    "total": 1,
    "forms": {
      "krumping": 1
    }
  },
  "yaw": {
    "total": 1,
    "forms": {
      "yaw": 1
    }
  },
  "hedda": {
    "total": 1,
    "forms": {
      "hedda": 1
    }
  },
  "blumentoft": {
    "total": 1,
    "forms": {
      "blumentoft": 1
    }
  }
}